hubspot_py_preprocessor/hubspot_py_preprocessor/__init__.py
hubspot_py_preprocessor/hubspot_py_preprocessor/cli.py
hubspot_py_preprocessor/inliner.py
hubspot_py_preprocessor/tests/__init__.py
hubspot_py_preprocessor-0.3.0.dist-info/METADATA
hubspot_py_preprocessor-0.3.0.dist-info/WHEEL
hubspot_py_preprocessor-0.3.0.dist-info/entry_points.txt
hubspot_py_preprocessor-0.3.0.dist-info/RECORD
