Metadata-Version: 2.3
Name: hubspot-py-preprocessor
Version: 0.3.0
Summary: A Python tool to extract and organize custom code for HubSpot customcode workflows.
Author: David BRAHIM
Requires-Python: >=3.8
Classifier: Programming Language :: Python :: 3
Classifier: Programming Language :: Python :: 3.8
Classifier: Programming Language :: Python :: 3.9
Classifier: Programming Language :: Python :: 3.10
Classifier: Programming Language :: Python :: 3.11
Classifier: Programming Language :: Python :: 3.12
Classifier: Programming Language :: Python :: 3.13
Requires-Dist: requests (>=2.32.3,<3.0.0)
